LICENSE
MANIFEST.in
README.rst
setup.py
biblion/__init__.py
biblion/admin.py
biblion/conf.py
biblion/exceptions.py
biblion/forms.py
biblion/managers.py
biblion/models.py
biblion/signals.py
biblion/urls.py
biblion/utils.py
biblion/views.py
biblion.egg-info/PKG-INFO
biblion.egg-info/SOURCES.txt
biblion.egg-info/dependency_links.txt
biblion.egg-info/not-zip-safe
biblion.egg-info/requires.txt
biblion.egg-info/top_level.txt
biblion/parsers/__init__.py
biblion/parsers/creole_parser.py
biblion/parsers/markdown_parser.py
biblion/templates/biblion/atom_entry.xml
biblion/templates/biblion/atom_feed.xml
biblion/templates/biblion/rss_feed.xml
biblion/templates/biblion/rss_item.xml
biblion/templatetags/__init__.py
biblion/templatetags/biblion_tags.py
biblion/tests/__init__.py
biblion/tests/models.py
biblion/tests/tests.py
biblion/tests/urls.py